Metadata-Version: 2.1
Name: portio
Version: 0.6.2
Summary: PortIO, python low level port I/O for Linux x86
Home-page: http://portio.inrim.it
Author: Fabrizio Pollastri
Author-email: Fabrizio Pollastri <mxgbot@gmail.com>
License: LGPL
Project-URL: Documentation, https://github.com/fabriziop/portio#readme
Project-URL: Issues, https://github.com/fabriziop/portio/issues
Project-URL: Source, https://github.com/fabriziop/portio
Platform: Linux
Classifier: Development Status :: 4 - Beta
Classifier: Programming Language :: Python
Classifier: Programming Language :: Python :: 3.8
Classifier: Programming Language :: Python :: 3.9
Classifier: Programming Language :: Python :: 3.10
Classifier: Programming Language :: Python :: 3.11
Classifier: Programming Language :: Python :: 3.12
Classifier: Programming Language :: Python :: 3.13
Classifier: Programming Language :: Python :: Implementation :: CPython
Classifier: Programming Language :: Python :: Implementation :: PyPy
Requires-Python: >=2.8
